echemdbconverters/__init__.py
echemdbconverters/baseloader.py
echemdbconverters/column_names.py
echemdbconverters/eclabloader.py
echemdbconverters/entrypoint.py
echemdbconverters/gamryloader.py
echemdbconverters/test/__init__.py
echemdbconverters/test/cli.py
echemdbconverters-0.4.1.dist-info/licenses/LICENSE
echemdbconverters-0.4.1.dist-info/METADATA
echemdbconverters-0.4.1.dist-info/WHEEL
echemdbconverters-0.4.1.dist-info/entry_points.txt
echemdbconverters-0.4.1.dist-info/top_level.txt
echemdbconverters-0.4.1.dist-info/RECORD
